wakong/Wakong.py
wakong/__init__.py
wakong/_generate_probs_list.py
wakong/apply_mask_scheme.py
wakong/constants.py
wakong/generate_mask_scheme.py
wakong/pretty_print_mask_scheme.py
wakong/probs_list.py
wakong-1.1.1.dist-info/LICENSE.txt
wakong-1.1.1.dist-info/WHEEL
wakong-1.1.1.dist-info/METADATA
wakong-1.1.1.dist-info/RECORD
