Metadata-Version: 2.1
Name: wakong
Version: 1.1.1
Summary: Wakong: An appropriate and robust masking algorithm for generating the training objective of text infilling.
Keywords: algorithm,masking algorithm,nlp,natural language processing,training objective,deep learning,text processing,text infilling
Author-email: Ayaka <ayaka@mail.shn.hk>
Requires-Python: ~=3.10
Classifier: Development Status :: 5 - Production/Stable
Classifier: Intended Audience :: Education
Classifier: Intended Audience :: Science/Research
Classifier: License :: CC0 1.0 Universal (CC0 1.0) Public Domain Dedication
Classifier: Operating System :: OS Independent
Classifier: Programming Language :: Python
Classifier: Programming Language :: Python :: 3
Classifier: Topic :: Scientific/Engineering :: Artificial Intelligence
Classifier: Topic :: Text Processing
Classifier: Typing :: Typed
Requires-Dist: numpyro~=0.10.1 ; extra == "test"
Project-URL: Repository, https://github.com/ayaka14732/wakong
Provides-Extra: test
